requests_random_user_agent/__init__.py
requests_random_user_agent/android_useragents.txt
requests_random_user_agent/useragents.txt
requests_random_user_agent-2023.10.25.dist-info/LICENSE
requests_random_user_agent-2023.10.25.dist-info/METADATA
requests_random_user_agent-2023.10.25.dist-info/WHEEL
requests_random_user_agent-2023.10.25.dist-info/top_level.txt
requests_random_user_agent-2023.10.25.dist-info/RECORD
