Metadata-Version: 2.2
Name: requests_random_user_agent
Version: 2023.10.25
Summary: Automatically generate a random User Agent for the requests library
Home-page: https://github.com/DavidWittman/requests-random-user-agent
Author: David Wittman
Author-email: david@wittman.com
Classifier: Programming Language :: Python :: 3
Classifier: Operating System :: OS Independent
License-File: LICENSE
Requires-Dist: requests<3.0.0,>=2.0.1
Dynamic: author
Dynamic: author-email
Dynamic: classifier
Dynamic: description
Dynamic: description-content-type
Dynamic: home-page
Dynamic: requires-dist
Dynamic: summary
